aflow/__init__.py
aflow/base.py
aflow/caster.py
aflow/control.py
aflow/entries.py
aflow/generators.py
aflow/keywords.py
aflow/msg.py
aflow/utility.py
aflow/templates/entry.py
aflow/templates/keywords.py
aflow-0.0.11.dist-info/LICENSE
aflow-0.0.11.dist-info/METADATA
aflow-0.0.11.dist-info/WHEEL
aflow-0.0.11.dist-info/top_level.txt
aflow-0.0.11.dist-info/RECORD
