Metadata-Version: 2.1
Name: aflow
Version: 0.0.11
Summary: Python API for searching AFLOW database.
Home-page: https://github.com/rosenbrockc/aflow
Author: Conrad W Rosenbrock
Author-email: rosenbrockc@gmail.com
License: MIT
Platform: UNKNOWN
Classifier: Development Status :: 4 - Beta
Classifier: Intended Audience :: Science/Research
Classifier: Natural Language :: English
Classifier: Operating System :: MacOS
Classifier: Operating System :: Microsoft :: Windows
Classifier: Programming Language :: Python
Classifier: Programming Language :: Python :: 2
Classifier: Programming Language :: Python :: 2.7
Classifier: Programming Language :: Python :: 3
Classifier: Programming Language :: Python :: 3.5
Requires-Dist: termcolor
Requires-Dist: numpy
Requires-Dist: six
Requires-Dist: jinja2
Requires-Dist: beautifulsoup4
Requires-Dist: ase
